rubiales_nlp/__init__.py
rubiales_nlp/base.py
rubiales_nlp/pipelines.py
rubiales_nlp/utils.py
rubiales_nlp-0.1.0.dist-info/WHEEL
rubiales_nlp-0.1.0.dist-info/METADATA
rubiales_nlp-0.1.0.dist-info/RECORD
