Metadata-Version: 2.1
Name: rubiales-nlp
Version: 0.1.0
Summary: Solve NLP common tasks
License: MIT
Author: Alberto Rubiales
Author-email: al.rubiales.b@gmail.com
Requires-Python: >=3.8,<=3.10
Classifier: License :: OSI Approved :: MIT License
Classifier: Programming Language :: Python :: 3
Classifier: Programming Language :: Python :: 3.10
Classifier: Programming Language :: Python :: 3.8
Classifier: Programming Language :: Python :: 3.9
Requires-Dist: black (>=21.12b0,<22.0)
Requires-Dist: flake8 (>=4.0.1,<5.0.0)
Requires-Dist: nltk (>=3.6.7,<4.0.0)
Requires-Dist: spacy (>=3.2.1,<4.0.0)
